LICENSE
MANIFEST.in
README.md
VERSION
create_docs.sh
pyproject.toml
requirements.txt
setup.py
docs/grib2io.html
docs/index.html
docs/search.js
docs/grib2io/tables.html
docs/grib2io/templates.html
docs/grib2io/utils.html
docs/grib2io/xarray_backend.html
docs/grib2io/tables/cf.html
docs/grib2io/tables/ndfd_additionals.html
docs/grib2io/tables/originating_centers.html
docs/grib2io/tables/section0.html
docs/grib2io/tables/section1.html
docs/grib2io/tables/section3.html
docs/grib2io/tables/section4.html
docs/grib2io/tables/section4_discipline0.html
docs/grib2io/tables/section4_discipline1.html
docs/grib2io/tables/section4_discipline10.html
docs/grib2io/tables/section4_discipline2.html
docs/grib2io/tables/section4_discipline20.html
docs/grib2io/tables/section4_discipline209.html
docs/grib2io/tables/section4_discipline3.html
docs/grib2io/tables/section4_discipline4.html
docs/grib2io/tables/section5.html
docs/grib2io/tables/section6.html
docs/grib2io/utils/arakawa_rotated_grid.html
docs/grib2io/utils/gauss_grid.html
docs/grib2io/utils/rotated_grid.html
src/ext/g2clib.pyx
src/ext/iplib.h
src/ext/iplib.pyx
src/ext/redtoreg.pyx
src/grib2io/__config__.py
src/grib2io/__init__.py
src/grib2io/_grib2io.py
src/grib2io/cf_standard_names.py
src/grib2io/templates.py
src/grib2io/xarray_backend.py
src/grib2io.egg-info/PKG-INFO
src/grib2io.egg-info/SOURCES.txt
src/grib2io.egg-info/dependency_links.txt
src/grib2io.egg-info/entry_points.txt
src/grib2io.egg-info/not-zip-safe
src/grib2io.egg-info/requires.txt
src/grib2io.egg-info/top_level.txt
src/grib2io/tables/__init__.py
src/grib2io/tables/cf.py
src/grib2io/tables/ndfd_additionals.py
src/grib2io/tables/originating_centers.py
src/grib2io/tables/section0.py
src/grib2io/tables/section1.py
src/grib2io/tables/section3.py
src/grib2io/tables/section4.py
src/grib2io/tables/section4_discipline0.py
src/grib2io/tables/section4_discipline1.py
src/grib2io/tables/section4_discipline10.py
src/grib2io/tables/section4_discipline2.py
src/grib2io/tables/section4_discipline20.py
src/grib2io/tables/section4_discipline209.py
src/grib2io/tables/section4_discipline3.py
src/grib2io/tables/section4_discipline4.py
src/grib2io/tables/section5.py
src/grib2io/tables/section6.py
src/grib2io/utils/__init__.py
