Metadata-Version: 2.4
Name: grib2io
Version: 2.6.0
Summary: Python interface to the NCEP G2C Library for reading/writing GRIB2 files.
Author-email: Eric Engle <eric.engle@noaa.gov>, Adam Schnapp <adam.schnapp@noaa.gov>
License: MIT
Project-URL: Documentation, https://noaa-mdl.github.io/grib2io
Project-URL: Respository, https://github.com/NOAA-MDL/grib2io
Keywords: weather,data-science,numpy,meteorology,weather-data,atmospheric-science,grib2,grib2-decoder,grib2-encoder,ncep
Classifier: Development Status :: 5 - Production/Stable
Classifier: Environment :: Console
Classifier: Programming Language :: Cython
Classifier: Programming Language :: Python :: 3
Classifier: Programming Language :: Python :: 3 :: Only
Classifier: Programming Language :: Python :: 3.8
Classifier: Programming Language :: Python :: 3.9
Classifier: Programming Language :: Python :: 3.10
Classifier: Programming Language :: Python :: 3.11
Classifier: Programming Language :: Python :: 3.12
Classifier: Programming Language :: Python :: 3.13
Classifier: Programming Language :: Python :: 3.14
Classifier: Intended Audience :: Science/Research
Classifier: License :: OSI Approved :: MIT License
Classifier: Topic :: Scientific/Engineering :: Atmospheric Science
Classifier: Topic :: Software Development :: Libraries :: Python Modules
Classifier: Operating System :: POSIX
Classifier: Operating System :: POSIX :: Linux
Classifier: Operating System :: MacOS
Requires-Python: <=3.14,>=3.8
License-File: LICENSE
Requires-Dist: numpy
Requires-Dist: pyproj
Provides-Extra: xarray
Requires-Dist: xarray; extra == "xarray"
Dynamic: license-file
